infineon_paco2_dps_lib/__init__.py
infineon_paco2_dps_lib/dps.py
infineon_paco2_dps_lib/paco2.py
infineon_paco2_dps_lib-0.1.7.dist-info/LICENSE
infineon_paco2_dps_lib-0.1.7.dist-info/METADATA
infineon_paco2_dps_lib-0.1.7.dist-info/WHEEL
infineon_paco2_dps_lib-0.1.7.dist-info/top_level.txt
infineon_paco2_dps_lib-0.1.7.dist-info/RECORD
