Metadata-Version: 2.1
Name: infineon-paco2-dps-lib
Version: 0.1.7
Summary: Library for interfacing with Infineon PA_CO2 and DPS sensors
Home-page: https://github.com/powenko/infineon_paco2_dps_lib
Author: Powen Ko
Author-email: powenkoads@gmail.com
Classifier: Programming Language :: Python :: 3
Classifier: License :: OSI Approved :: MIT License
Classifier: Operating System :: OS Independent
Requires-Python: >=3.6
License-File: LICENSE
Requires-Dist: smbus2
